{"nodes": [{"id": "users_sergeogah_documents_dev_projects_k_insight_route_object_md", "label": "route-object.md", "file_type": "document", "source_file": "route-object.md", "source_location": "L1"}, {"id": "k_insight_route_object_route_object", "label": "Route Object", "file_type": "document", "source_file": "route-object.md", "source_location": "L6"}, {"id": "k_insight_route_object_introduction", "label": "Introduction", "file_type": "document", "source_file": "route-object.md", "source_location": "L10"}, {"id": "k_insight_route_object_component", "label": "Component", "file_type": "document", "source_file": "route-object.md", "source_location": "L33"}, {"id": "k_insight_route_object_middleware", "label": "`middleware`", "file_type": "document", "source_file": "route-object.md", "source_location": "L57"}, {"id": "k_insight_route_object_loader", "label": "`loader`", "file_type": "document", "source_file": "route-object.md", "source_location": "L104"}, {"id": "k_insight_route_object_action", "label": "`action`", "file_type": "document", "source_file": "route-object.md", "source_location": "L136"}, {"id": "k_insight_route_object_shouldrevalidate", "label": "`shouldRevalidate`", "file_type": "document", "source_file": "route-object.md", "source_location": "L187"}, {"id": "k_insight_route_object_lazy", "label": "`lazy`", "file_type": "document", "source_file": "route-object.md", "source_location": "L223"}, {"id": "k_insight_route_object_handle", "label": "`handle`", "file_type": "document", "source_file": "route-object.md", "source_location": "L243"}], "edges": [{"source": "users_sergeogah_documents_dev_projects_k_insight_route_object_md", "target": "k_insight_route_object_route_object", "relation": "contains", "confidence": "EXTRACTED", "source_file": "route-object.md", "source_location": "L6", "weight": 1.0}, {"source": "k_insight_route_object_route_object", "target": "k_insight_route_object_introduction", "relation": "contains", "confidence": "EXTRACTED", "source_file": "route-object.md", "source_location": "L10", "weight": 1.0}, {"source": "k_insight_route_object_route_object", "target": "k_insight_route_object_component", "relation": "contains", "confidence": "EXTRACTED", "source_file": "route-object.md", "source_location": "L33", "weight": 1.0}, {"source": "k_insight_route_object_route_object", "target": "k_insight_route_object_middleware", "relation": "contains", "confidence": "EXTRACTED", "source_file": "route-object.md", "source_location": "L57", "weight": 1.0}, {"source": "k_insight_route_object_route_object", "target": "k_insight_route_object_loader", "relation": "contains", "confidence": "EXTRACTED", "source_file": "route-object.md", "source_location": "L104", "weight": 1.0}, {"source": "k_insight_route_object_route_object", "target": "k_insight_route_object_action", "relation": "contains", "confidence": "EXTRACTED", "source_file": "route-object.md", "source_location": "L136", "weight": 1.0}, {"source": "k_insight_route_object_route_object", "target": "k_insight_route_object_shouldrevalidate", "relation": "contains", "confidence": "EXTRACTED", "source_file": "route-object.md", "source_location": "L187", "weight": 1.0}, {"source": "users_sergeogah_documents_dev_projects_k_insight_route_object_md", "target": "users_sergeogah_documents_dev_projects_modes_md", "relation": "references", "confidence": "EXTRACTED", "source_file": "route-object.md", "source_location": "L221", "weight": 1.0}, {"source": "k_insight_route_object_route_object", "target": "k_insight_route_object_lazy", "relation": "contains", "confidence": "EXTRACTED", "source_file": "route-object.md", "source_location": "L223", "weight": 1.0}, {"source": "k_insight_route_object_route_object", "target": "k_insight_route_object_handle", "relation": "contains", "confidence": "EXTRACTED", "source_file": "route-object.md", "source_location": "L243", "weight": 1.0}, {"source": "users_sergeogah_documents_dev_projects_k_insight_route_object_md", "target": "users_sergeogah_documents_dev_projects_k_insight_data_loading_md", "relation": "references", "confidence": "EXTRACTED", "source_file": "route-object.md", "source_location": "L264", "weight": 1.0}, {"source": "users_sergeogah_documents_dev_projects_k_insight_route_object_md", "target": "users_sergeogah_documents_how_to_middleware_md", "relation": "references", "confidence": "EXTRACTED", "source_file": "route-object.md", "source_location": "L267", "weight": 1.0}, {"source": "users_sergeogah_documents_dev_projects_k_insight_route_object_md", "target": "users_sergeogah_documents_api_hooks_usematches_md", "relation": "references", "confidence": "EXTRACTED", "source_file": "route-object.md", "source_location": "L268", "weight": 1.0}], "input_tokens": 0, "output_tokens": 0}