{"nodes": [{"id": "users_sergeogah_documents_dev_projects_k_insight_knowledge_finance_finance_kpis_md", "label": "finance_kpis.md", "file_type": "document", "source_file": "knowledge/finance/finance_kpis.md", "source_location": "L1"}, {"id": "finance_finance_kpis_kpi_finance", "label": "KPI Finance", "file_type": "document", "source_file": "knowledge/finance/finance_kpis.md", "source_location": "L1"}, {"id": "finance_finance_kpis_indicateurs_principaux", "label": "Indicateurs principaux", "file_type": "document", "source_file": "knowledge/finance/finance_kpis.md", "source_location": "L5"}, {"id": "finance_finance_kpis_axes_d_analyse", "label": "Axes d'analyse", "file_type": "document", "source_file": "knowledge/finance/finance_kpis.md", "source_location": "L15"}], "edges": [{"source": "users_sergeogah_documents_dev_projects_k_insight_knowledge_finance_finance_kpis_md", "target": "finance_finance_kpis_kpi_finance", "relation": "contains", "confidence": "EXTRACTED", "source_file": "knowledge/finance/finance_kpis.md", "source_location": "L1", "weight": 1.0}, {"source": "finance_finance_kpis_kpi_finance", "target": "finance_finance_kpis_indicateurs_principaux", "relation": "contains", "confidence": "EXTRACTED", "source_file": "knowledge/finance/finance_kpis.md", "source_location": "L5", "weight": 1.0}, {"source": "finance_finance_kpis_kpi_finance", "target": "finance_finance_kpis_axes_d_analyse", "relation": "contains", "confidence": "EXTRACTED", "source_file": "knowledge/finance/finance_kpis.md", "source_location": "L15", "weight": 1.0}], "input_tokens": 0, "output_tokens": 0}